changelog_gen/__init__.py
changelog_gen/config.py
changelog_gen/context.py
changelog_gen/errors.py
changelog_gen/extractor.py
changelog_gen/parse.py
changelog_gen/post_processor.py
changelog_gen/util.py
changelog_gen/vcs.py
changelog_gen/version.py
changelog_gen/writer.py
changelog_gen/cli/__init__.py
changelog_gen/cli/command.py
changelog_gen/cli/util.py
changelog_gen-0.14.0.dist-info/METADATA
changelog_gen-0.14.0.dist-info/WHEEL
changelog_gen-0.14.0.dist-info/entry_points.txt
changelog_gen-0.14.0.dist-info/licenses/LICENSE
changelog_gen-0.14.0.dist-info/RECORD
