Metadata-Version: 2.4
Name: changelog_gen
Version: 0.14.0
Summary: Changelog generation tool
Project-URL: homepage, https://github.com/NRWLDev/changelog-gen/
Project-URL: documentation, https://nrwldev.github.io/changelog-gen/
Author-email: Daniel Edgecombe <daniel@nrwl.co>
Maintainer-email: Daniel Edgecombe <daniel@nrwl.co>
License-Expression: Apache-2.0
License-File: LICENSE
Keywords: bumpversion,changelog,release,version
Classifier: Development Status :: 4 - Beta
Classifier: Environment :: Console
Classifier: Intended Audience :: Developers
Classifier: License :: OSI Approved :: Apache Software License
Classifier: Operating System :: OS Independent
Classifier: Programming Language :: Python
Classifier: Programming Language :: Python :: 3
Classifier: Programming Language :: Python :: 3 :: Only
Classifier: Programming Language :: Python :: 3.10
Classifier: Programming Language :: Python :: 3.11
Classifier: Programming Language :: Python :: 3.12
Classifier: Programming Language :: Python :: 3.13
Classifier: Programming Language :: Python :: 3.14
Classifier: Topic :: Software Development :: Build Tools
Classifier: Topic :: Software Development :: Version Control
Classifier: Topic :: System :: Software Distribution
Requires-Python: >=3.10
Requires-Dist: gitpython
Requires-Dist: jinja2
Requires-Dist: pygments
Requires-Dist: rtoml
Requires-Dist: typer-slim
Requires-Dist: typing-extensions>=4.7.0; python_version <= '3.10'
Provides-Extra: dev
Requires-Dist: pre-commit>=3.0.2; extra == 'dev'
Requires-Dist: ruff>=0.14.10; extra == 'dev'
Provides-Extra: post-process
Requires-Dist: auth-aws4; extra == 'post-process'
Requires-Dist: httpx; extra == 'post-process'
Provides-Extra: test
Requires-Dist: auth-aws4>=0; extra == 'test'
Requires-Dist: freezegun>=1.2.1; extra == 'test'
Requires-Dist: httpx>=0; extra == 'test'
Requires-Dist: path<17,>=16; extra == 'test'
Requires-Dist: pytest-cov>=7.0.0; extra == 'test'
Requires-Dist: pytest-git<1.8,>=1.7.0; extra == 'test'
Requires-Dist: pytest-httpx>=0.36.0; extra == 'test'
Requires-Dist: pytest-random-order>=1.2.0; extra == 'test'
Requires-Dist: pytest>=9.0.0; extra == 'test'
